notmiwae_pytorch/__init__.py
notmiwae_pytorch/trainer.py
notmiwae_pytorch/utils.py
notmiwae_pytorch/models/__init__.py
notmiwae_pytorch/models/base.py
notmiwae_pytorch/models/miwae.py
notmiwae_pytorch/models/notmiwae.py
notmiwae_pytorch/models/supmiwae.py
notmiwae_pytorch/models/supnotmiwae.py
notmiwae_pytorch-0.1.3.dist-info/licenses/LICENSE
notmiwae_pytorch-0.1.3.dist-info/METADATA
notmiwae_pytorch-0.1.3.dist-info/WHEEL
notmiwae_pytorch-0.1.3.dist-info/top_level.txt
notmiwae_pytorch-0.1.3.dist-info/RECORD
