Metadata-Version: 2.4
Name: notmiwae-pytorch
Version: 0.1.3
Summary: Not-MIWAE: Deep Generative Modelling with Missing Not at Random Data
Author-email: Adam Gassem <adam.gassem@ensta.fr>, Amine Maazizi <amine.maazizi@ensta.fr>, Ewerthon Melzani <ewerthon.melzani@ensta.fr>
License-Expression: MIT
Project-URL: Homepage, https://github.com/Adam-Ousse/notmiwae_pytorch
Project-URL: Repository, https://github.com/Adam-Ousse/notmiwae_pytorch
Project-URL: Issues, https://github.com/Adam-Ousse/notmiwae_pytorch/issues
Keywords: deep-learning,pytorch,missing-data,imputation,variational-autoencoder,MNAR,MIWAE,impute
Classifier: Development Status :: 3 - Alpha
Classifier: Intended Audience :: Science/Research
Classifier: Operating System :: OS Independent
Classifier: Programming Language :: Python :: 3
Classifier: Programming Language :: Python :: 3.8
Classifier: Programming Language :: Python :: 3.9
Classifier: Programming Language :: Python :: 3.10
Classifier: Programming Language :: Python :: 3.11
Classifier: Programming Language :: Python :: 3.12
Classifier: Topic :: Scientific/Engineering :: Artificial Intelligence
Requires-Python: >=3.8
License-File: LICENSE
Requires-Dist: torch>=1.9.0
Requires-Dist: numpy>=1.19.0
Requires-Dist: tqdm>=4.60.0
Provides-Extra: dev
Requires-Dist: pytest>=6.0; extra == "dev"
Requires-Dist: pytest-cov>=2.0; extra == "dev"
Requires-Dist: black>=22.0; extra == "dev"
Requires-Dist: isort>=5.0; extra == "dev"
Requires-Dist: flake8>=4.0; extra == "dev"
Provides-Extra: notebooks
Requires-Dist: jupyter>=1.0; extra == "notebooks"
Requires-Dist: matplotlib>=3.3; extra == "notebooks"
Requires-Dist: pandas>=1.2; extra == "notebooks"
Requires-Dist: scikit-learn>=0.24; extra == "notebooks"
Requires-Dist: torchvision>=0.10; extra == "notebooks"
Provides-Extra: all
Requires-Dist: notmiwae-pytorch[dev,notebooks]; extra == "all"
Dynamic: license-file
